snex/__init__.py
snex/core.py
snex/fp.py
snex/util.py
snex/cli/__init__.py
snex/templates/python-url.snex.conf.yaml
snex/templates/python.snex.conf.yaml
snex/templates/swift.snex.conf.yaml
snex-3000.2.1.dist-info/LICENSE
snex-3000.2.1.dist-info/METADATA
snex-3000.2.1.dist-info/WHEEL
snex-3000.2.1.dist-info/entry_points.txt
snex-3000.2.1.dist-info/top_level.txt
snex-3000.2.1.dist-info/RECORD
