Metadata-Version: 2.1
Name: snex
Version: 3000.2.1
Summary: snex - snippet extractor
Author-email: Joachim Bargsten <jw@bargsten.org>
License: Apache-2.0
Project-URL: homepage, https://github.com/jwbargsten/snex
Project-URL: repository, https://github.com/jwbargsten/snex
Project-URL: documentation, https://github.com/jwbargsten/snex
Requires-Python: >=3.10
License-File: LICENSE
Requires-Dist: requests
Requires-Dist: pyyaml
Requires-Dist: more-itertools
Requires-Dist: click >=8.0.0
Requires-Dist: chevron
Requires-Dist: Jinja2
Requires-Dist: pathspec
Provides-Extra: build
Requires-Dist: snex[dev] ; extra == 'build'
Requires-Dist: build ; extra == 'build'
Requires-Dist: twine ; extra == 'build'
Requires-Dist: tomli ; extra == 'build'
Requires-Dist: check-manifest ; extra == 'build'
Requires-Dist: check-wheel-contents ; extra == 'build'
Requires-Dist: pyroma ; extra == 'build'
Provides-Extra: dev
Requires-Dist: setuptools-scm ; extra == 'dev'
Requires-Dist: pytest >=7 ; extra == 'dev'
Requires-Dist: ruff ; extra == 'dev'
Requires-Dist: mypy ; extra == 'dev'
